jk_etcpasswd/GrpFile.py
jk_etcpasswd/GrpRecord.py
jk_etcpasswd/PwdFile.py
jk_etcpasswd/PwdRecord.py
jk_etcpasswd/__init__.py
jk_etcpasswd-0.2025.6.12.dist-info/WHEEL
jk_etcpasswd-0.2025.6.12.dist-info/METADATA
jk_etcpasswd-0.2025.6.12.dist-info/RECORD
