Metadata-Version: 2.1
Name: jk_etcpasswd
Version: 0.2025.6.12
Summary: This python module provides classes to parse and model data from /etc/passwd, /etc/shadow, /etc/group and /etc/gshadow.
Keywords: passwd,sysadmin
Author-email: Jürgen Knauth <pubsrc@binary-overflow.de>
Maintainer-email: Jürgen Knauth <pubsrc@binary-overflow.de>
Requires-Python: >=3.8
Classifier: Development Status :: 5 - Production/Stable
Classifier: License :: OSI Approved :: Apache Software License
Classifier: Programming Language :: Python :: 3
Requires-Dist: jk_typing >= 0.2025.2.1
Requires-Dist: jk_prettyprintobj >= 0.2025.2.1
